requests_engine/__init__.py
requests_engine/conversation.py
requests_engine/engine.py
requests_engine/model_pricing.py
requests_engine/providers/__init__.py
requests_engine/providers/abstract_provider.py
requests_engine/providers/aws_anthropic_provider.py
requests_engine/providers/gcp_beta_completions_provider.py
requests_engine/providers/openai_compatible_api_provider.py
requests_engine-0.1.1.dist-info/METADATA
requests_engine-0.1.1.dist-info/WHEEL
requests_engine-0.1.1.dist-info/licenses/LICENSE.md
requests_engine-0.1.1.dist-info/RECORD
