Metadata-Version: 2.3
Name: requests-engine
Version: 0.1.1
Summary: A simple library for performing LLM batch inference using API requests. 
Project-URL: Homepage, https://github.com/EdoardoLuciani/requests_engine
Author-email: EdoardoLuciani <edoardo.luciani@gmail.com>
License-File: LICENSE.md
Classifier: License :: OSI Approved :: MIT License
Classifier: Programming Language :: Python :: 3
Requires-Python: >=3.8
Requires-Dist: aiohttp
Requires-Dist: botocore
Requires-Dist: google-auth
Requires-Dist: requests
